unipress/__init__.py
unipress/approximations.py
unipress-1.4.dist-info/LICENSE
unipress-1.4.dist-info/METADATA
unipress-1.4.dist-info/WHEEL
unipress-1.4.dist-info/top_level.txt
unipress-1.4.dist-info/RECORD
