Metadata-Version: 2.1
Name: unipress
Version: 1.4
Summary: This is a library developed by Institute of High Pressure Physics of Polish Academy of Sciences.
Author: Konrad Sakowski
Platform: any
Classifier: Programming Language :: Python :: 3
Classifier: License :: OSI Approved :: Apache Software License
Classifier: Operating System :: OS Independent
Requires-Python: >=3.6
License-File: LICENSE
Requires-Dist: numpy
Requires-Dist: pint
Requires-Dist: scipy
